wordfreq_lemma/__init__.py
wordfreq_lemma/lemma.py
wordfreq_lemma/utils.py
wordfreq_lemma-1.0.dist-info/METADATA
wordfreq_lemma-1.0.dist-info/WHEEL
wordfreq_lemma-1.0.dist-info/top_level.txt
wordfreq_lemma-1.0.dist-info/RECORD
