Metadata-Version: 2.1
Name: wordfreq-lemma
Version: 1.0
Summary: Lemmatized Word Frequency
Home-page: 
Author: Hao Wu
Author-email: haowu@dataset.sh
Requires: nltk
